README.txt
setup.py
edo_client/__init__.py
edo_client/cached.py
edo_client/client.py
edo_client/error.py
edo_client/memcache.py
edo_client.egg-info/PKG-INFO
edo_client.egg-info/SOURCES.txt
edo_client.egg-info/dependency_links.txt
edo_client.egg-info/requires.txt
edo_client.egg-info/top_level.txt
edo_client/api/__init__.py
edo_client/api/account.py
edo_client/api/admin.py
edo_client/api/auth.py
edo_client/api/base.py
edo_client/api/content.py
edo_client/api/message.py
edo_client/api/oauth2.py
edo_client/api/operator.py
edo_client/api/org.py
edo_client/api/package.py
edo_client/api/session.py
edo_client/api/viewer.py