Metadata-Version: 1.1
Name: edo-client
Version: 0.9.3
Summary: SDK for easydo.cn
Home-page: https://github.com/everydo/python-sdk
Author: Chen Weihong
Author-email: whchen1080@gmail.com
License: UNKNOWN
Download-URL: https://github.com/everydo/python-sdk
Platform: UNKNOWN
Classifier: Development Status :: 5 - Production/Stable
Classifier: Environment :: Web Environment
Classifier: Intended Audience :: Developers
Classifier: License :: OSI Approved :: MIT License
Classifier: Operating System :: OS Independent
Classifier: Programming Language :: Python
Classifier: Topic :: Internet
Classifier: Topic :: Software Development :: Libraries :: Python Modules
